skroute/__init__.py
skroute/cluster/__init__.py
skroute/cluster/kmeans_truncate.py
skroute/_utils/_utils.c
skroute/_utils/_utils.cpython-37m-x86_64-linux-gnu.so
skroute/_validators/__init__.py
skroute/_validators/_validators.py
skroute/metaheuristics/__init__.py
skroute/metaheuristics/genetics/__init__.py
skroute/metaheuristics/genetics/_base_ensemble_genetics.py
skroute/metaheuristics/genetics/_base_genetics/_base_genetic.c
skroute/metaheuristics/genetics/_base_genetics/_base_genetic.cpython-37m-x86_64-linux-gnu.so
skroute/metaheuristics/genetics/_base_genetics/_utils_genetic.c
skroute/metaheuristics/genetics/_base_genetics/_utils_genetic.cpython-37m-x86_64-linux-gnu.so
skroute/metaheuristics/simulated_annealing/__init__.py
skroute/metaheuristics/simulated_annealing/_base_ensemble_simulated_annealing.py
skroute/metaheuristics/simulated_annealing/_base_simulated_annealing/_utils_sa.c
skroute/metaheuristics/simulated_annealing/_base_simulated_annealing/_utils_sa.cpython-37m-x86_64-linux-gnu.so
skroute/metaheuristics/simulated_annealing/_base_simulated_annealing/_base_simulated_annealing.cpython-37m-x86_64-linux-gnu.so
skroute/metaheuristics/simulated_annealing/_base_simulated_annealing/_base_simulated_annealing.c
skroute/metaheuristics/som/__init__.py
skroute/metaheuristics/som/_som_validators.py
skroute/metaheuristics/som/_utils_som.py
skroute/metaheuristics/som/som.py
skroute/metaheuristics/tabu_search/_tabu_search.py
skroute/metaheuristics/tabu_search/__init__.py
skroute/metaheuristics/tabu_search/_utils_tabu.py
skroute/metaheuristics/tabu_search/pruebas_tabu.py
skroute/datasets/ja9847.tsp
skroute/datasets/kz9976.tsp
skroute/datasets/Alicante-Murcia_places.pkl
skroute/datasets/wi29.tsp
skroute/datasets/__init__.py
skroute/datasets/qa194.tsp
skroute/datasets/df_qatar_costs.pkl
skroute/datasets/it16862.tsp
skroute/datasets/rw1621.tsp
skroute/datasets/bm33708.tsp
skroute/datasets/mu1979.tsp
skroute/datasets/pm8079.tsp
skroute-1.0.0a1.dist-info/WHEEL
skroute-1.0.0a1.dist-info/top_level.txt
skroute-1.0.0a1.dist-info/RECORD
skroute-1.0.0a1.dist-info/METADATA
