Metadata-Version: 2.1
Name: skroute
Version: 1.0.0a1
Summary: Compute Routes easy and fast
Home-page: https://github.com/arubiales/scikit-route
Author: Alberto Rubiales
Author-email: al.rubiales.b@gmail.com
License: MIT License
Platform: UNKNOWN
Classifier: License :: OSI Approved :: MIT License
Classifier: Programming Language :: Python
Classifier: Programming Language :: Python :: 3.6
Classifier: Programming Language :: Python :: 3.7
Classifier: Programming Language :: Python :: 3.8
Classifier: Programming Language :: Python :: 3.9
Requires-Dist: absl-py (==0.11.0)
Requires-Dist: astunparse (==1.6.3)
Requires-Dist: attrs (==20.3.0)
Requires-Dist: cachetools (==4.2.0)
Requires-Dist: certifi (==2020.12.5)
Requires-Dist: chardet (==4.0.0)
Requires-Dist: coverage (==5.3.1)
Requires-Dist: Cython (==0.29.21)
Requires-Dist: flatbuffers (==1.12)
Requires-Dist: gast (==0.3.3)
Requires-Dist: google-auth (==1.24.0)
Requires-Dist: google-auth-oauthlib (==0.4.2)
Requires-Dist: google-pasta (==0.2.0)
Requires-Dist: googlemaps (==4.4.2)
Requires-Dist: grpcio (==1.32.0)
Requires-Dist: h5py (==2.10.0)
Requires-Dist: idna (==2.10)
Requires-Dist: iniconfig (==1.1.1)
Requires-Dist: joblib (==1.0.0)
Requires-Dist: Keras-Preprocessing (>=1.0.0)
Requires-Dist: Markdown (==3.3.3)
Requires-Dist: numpy (>=1.18.0)
Requires-Dist: oauthlib (==3.1.0)
Requires-Dist: opt-einsum (==3.3.0)
Requires-Dist: packaging (==20.8)
Requires-Dist: pandas (>=1.0.0)
Requires-Dist: pluggy (==0.13.1)
Requires-Dist: protobuf (==3.14.0)
Requires-Dist: py (==1.10.0)
Requires-Dist: pyasn1 (==0.4.8)
Requires-Dist: pyasn1-modules (==0.2.8)
Requires-Dist: pyparsing (==2.4.7)
Requires-Dist: pytest (==6.2.1)
Requires-Dist: pytest-cov (==2.10.1)
Requires-Dist: python-dateutil (==2.8.1)
Requires-Dist: pytz (==2020.5)
Requires-Dist: requests (==2.25.1)
Requires-Dist: requests-oauthlib (==1.3.0)
Requires-Dist: rsa (==4.6)
Requires-Dist: scikit-learn (>=0.22.0)
Requires-Dist: scipy (==1.5.4)
Requires-Dist: six (==1.15.0)
Requires-Dist: tensorboard (>=2.1.0)
Requires-Dist: tensorboard-plugin-wit (==1.7.0)
Requires-Dist: tensorflow (>=2.1.0)
Requires-Dist: tensorflow-estimator (>=2.1.0)
Requires-Dist: termcolor (==1.1.0)
Requires-Dist: threadpoolctl (==2.1.0)
Requires-Dist: toml (==0.10.2)
Requires-Dist: tqdm (==4.55.0)
Requires-Dist: typing-extensions (==3.7.4.3)
Requires-Dist: urllib3 (==1.26.2)
Requires-Dist: Werkzeug (==1.0.1)
Requires-Dist: wrapt (==1.12.1)
